[
  {
    "SchemaName": "WechatOfficialAccount",
    "AllowNull": false,
    "ControlType": "TextBox",
    "DefaultValue": "",
    "Indexable": false,
    "IsSystemField": false,
    "Label": "Token",
    "Length": 0,
    "Modifiable": true,
    "Name": "Token",
    "Order": 0,
    "ShowInGrid": true,
    "Tooltip": "",
    "Id": "5e69a388e4064e799bd32963ffed6a1c",
    "CreatedOn": "2016-11-27T10:59:16.3435777Z",
    "UpdatedOn": "2016-11-27T10:59:16.3435777Z"
  },
  {
    "SchemaName": "WechatOfficialAccount",
    "AllowNull": false,
    "ControlType": "TextBox",
    "DefaultValue": "",
    "Indexable": false,
    "IsSystemField": false,
    "Label": "EncodingAESKey",
    "Length": 0,
    "Modifiable": true,
    "Name": "EncodingAESKey",
    "Order": 0,
    "ShowInGrid": true,
    "Tooltip": "",
    "Id": "76345a5bd7e44dbaabef24dff7381409",
    "CreatedOn": "2016-11-27T10:59:16.348578Z",
    "UpdatedOn": "2016-11-27T10:59:16.348578Z"
  },
  {
    "SchemaName": "WechatOfficialAccount",
    "AllowNull": false,
    "ControlType": "TextBox",
    "DefaultValue": "",
    "Indexable": false,
    "IsSystemField": false,
    "Label": "AppID",
    "Length": 0,
    "Modifiable": true,
    "Name": "AppID",
    "Order": 0,
    "ShowInGrid": true,
    "Tooltip": "",
    "Id": "38a2ef730fbc487dbfe1c6ccfa96665c",
    "CreatedOn": "2016-11-27T10:59:16.3725794Z",
    "UpdatedOn": "2016-11-27T10:59:16.3725794Z"
  },
  {
    "SchemaName": "WechatOfficialAccount",
    "AllowNull": false,
    "ControlType": "TextBox",
    "DefaultValue": "",
    "Indexable": false,
    "IsSystemField": false,
    "Label": "AppSecret",
    "Length": 0,
    "Modifiable": true,
    "Name": "AppSecret",
    "Order": 0,
    "ShowInGrid": true,
    "Tooltip": "",
    "Id": "0156557f1d2e4cf582805592681c9b0f",
    "CreatedOn": "2016-11-27T10:59:16.3755796Z",
    "UpdatedOn": "2016-11-27T10:59:16.3755796Z"
  },
  {
    "SchemaName": "WechatOfficialAccount",
    "AllowNull": false,
    "ControlType": "TextBox",
    "DefaultValue": "",
    "Indexable": false,
    "IsSystemField": false,
    "Label": "Name",
    "Length": 0,
    "Modifiable": true,
    "Name": "Name",
    "Order": 0,
    "ShowInGrid": true,
    "Tooltip": "",
    "Id": "9d56e65ec9c94fa6b8655680d56d31b4",
    "CreatedOn": "2016-11-27T10:59:16.3785797Z",
    "UpdatedOn": "2016-11-27T10:59:16.3785797Z"
  },
  {
    "SchemaName": "WechatOfficialAccount",
    "AllowNull": false,
    "ControlType": "TextBox",
    "DefaultValue": "",
    "Indexable": false,
    "IsSystemField": false,
    "Label": "OpenId",
    "Length": 0,
    "Modifiable": true,
    "Name": "OpenId",
    "Order": 0,
    "ShowInGrid": true,
    "Tooltip": "",
    "Id": "3f19519b43084d35ad32237ddcd030bf",
    "CreatedOn": "2016-11-27T10:59:16.3815799Z",
    "UpdatedOn": "2016-11-27T10:59:16.3815799Z"
  },
  {
    "SchemaName": "WechatOfficialAccount",
    "AllowNull": false,
    "ControlType": "TextBox",
    "DefaultValue": "",
    "Indexable": false,
    "IsSystemField": false,
    "Label": "IsServiceAccount",
    "Length": 0,
    "Modifiable": true,
    "Name": "IsServiceAccount",
    "Order": 0,
    "ShowInGrid": true,
    "Tooltip": "",
    "Id": "147a09463af3414fac20bb1e5a26acfb",
    "CreatedOn": "2016-11-27T10:59:16.3845801Z",
    "UpdatedOn": "2016-11-27T10:59:16.3845801Z"
  },
  {
    "SchemaName": "WechatOfficialAccount",
    "AllowNull": false,
    "ControlType": "Hidden",
    "DefaultValue": null,
    "Indexable": false,
    "IsSystemField": true,
    "Label": "Id",
    "Length": 0,
    "Modifiable": false,
    "Name": "Id",
    "Order": 0,
    "ShowInGrid": false,
    "Tooltip": null,
    "Id": "a7500924248140859f4e4b2722087078",
    "CreatedOn": "2016-11-27T10:59:16.3875802Z",
    "UpdatedOn": "2016-11-27T10:59:16.3875802Z"
  },
  {
    "SchemaName": "WechatOfficialAccount",
    "AllowNull": true,
    "ControlType": "TextBox",
    "DefaultValue": "",
    "Indexable": false,
    "IsSystemField": true,
    "Label": "User Key",
    "Length": 0,
    "Modifiable": false,
    "Name": "UserKey",
    "Order": 100,
    "ShowInGrid": false,
    "Tooltip": "An user and SEO friendly content key, it is mostly used to customize the page URL",
    "Id": "355ec14aaef9440eb6962240b0cabcc3",
    "CreatedOn": "2016-11-27T10:59:16.3915805Z",
    "UpdatedOn": "2016-11-27T10:59:16.3915805Z"
  },
  {
    "SchemaName": "WechatOfficialAccount",
    "AllowNull": true,
    "ControlType": "Hidden",
    "DefaultValue": null,
    "Indexable": false,
    "IsSystemField": true,
    "Label": "Created Time",
    "Length": 0,
    "Modifiable": false,
    "Name": "CreatedOn",
    "Order": 98,
    "ShowInGrid": true,
    "Tooltip": null,
    "Id": "118047abd2b6484fa8edf950b91acc62",
    "CreatedOn": "2016-11-27T10:59:16.3965808Z",
    "UpdatedOn": "2016-11-27T10:59:16.3965808Z"
  },
  {
    "SchemaName": "WechatOfficialAccount",
    "AllowNull": false,
    "ControlType": "Hidden",
    "DefaultValue": null,
    "Indexable": false,
    "IsSystemField": true,
    "Label": "Updated Time",
    "Length": 0,
    "Modifiable": false,
    "Name": "UpdatedOn",
    "Order": 98,
    "ShowInGrid": false,
    "Tooltip": null,
    "Id": "2941580fb08348eeba28c93d92577654",
    "CreatedOn": "2016-11-27T10:59:16.401581Z",
    "UpdatedOn": "2016-11-27T10:59:16.401581Z"
  },
  {
    "SchemaName": "WechatOfficialAccount",
    "AllowNull": false,
    "ControlType": "Hidden",
    "DefaultValue": null,
    "Indexable": false,
    "IsSystemField": true,
    "Label": "UpdatedBy",
    "Length": 0,
    "Modifiable": false,
    "Name": "UpdatedBy",
    "Order": 99,
    "ShowInGrid": false,
    "Tooltip": null,
    "Id": "50bfc6c8a3374eeb922f86f08f5e1d47",
    "CreatedOn": "2016-11-27T10:59:16.4055813Z",
    "UpdatedOn": "2016-11-27T10:59:16.4055813Z"
  },
  {
    "SchemaName": "WechatOfficialAccount",
    "AllowNull": false,
    "ControlType": "Hidden",
    "DefaultValue": null,
    "Indexable": false,
    "IsSystemField": true,
    "Label": "CreatedBy",
    "Length": 0,
    "Modifiable": false,
    "Name": "CreatedBy",
    "Order": 0,
    "ShowInGrid": false,
    "Tooltip": null,
    "Id": "a8504d7dd6c94fb991562afea18cc24e",
    "CreatedOn": "2016-11-27T10:59:16.4095815Z",
    "UpdatedOn": "2016-11-27T10:59:16.4095815Z"
  },
  {
    "SchemaName": "WechatOfficialAccount",
    "AllowNull": false,
    "ControlType": "Hidden",
    "DefaultValue": null,
    "Indexable": false,
    "IsSystemField": true,
    "Label": "Status",
    "Length": 0,
    "Modifiable": false,
    "Name": "Status",
    "Order": 99,
    "ShowInGrid": false,
    "Tooltip": null,
    "Id": "8c4b01f173d0477a9f947506bcaf5c2d",
    "CreatedOn": "2016-11-27T10:59:16.4125817Z",
    "UpdatedOn": "2016-11-27T10:59:16.4125817Z"
  },
  {
    "SchemaName": "WechatMaterial",
    "AllowNull": false,
    "ControlType": "TextBox",
    "DefaultValue": "",
    "Indexable": false,
    "IsSystemField": false,
    "Label": "OfficialAccount",
    "Length": 0,
    "Modifiable": true,
    "Name": "OfficialAccount",
    "Order": 0,
    "ShowInGrid": true,
    "Tooltip": "",
    "Id": "62f9d53ffe8c4ad7b21819baad7e3d2f",
    "CreatedOn": "2016-11-27T13:34:58.682874Z",
    "UpdatedOn": "2016-11-27T13:34:58.682874Z"
  },
  {
    "SchemaName": "WechatMaterial",
    "AllowNull": false,
    "ControlType": "TextBox",
    "DefaultValue": "",
    "Indexable": false,
    "IsSystemField": false,
    "Label": "Type",
    "Length": 0,
    "Modifiable": true,
    "Name": "Type",
    "Order": 0,
    "ShowInGrid": true,
    "Tooltip": "",
    "Id": "72795f1d9a7d4129a684586c38a980f1",
    "CreatedOn": "2016-11-27T13:35:07.9124019Z",
    "UpdatedOn": "2016-11-27T13:35:07.9124019Z"
  },
  {
    "SchemaName": "WechatMaterial",
    "AllowNull": false,
    "ControlType": "TextBox",
    "DefaultValue": "",
    "Indexable": false,
    "IsSystemField": false,
    "Label": "MediaId",
    "Length": 0,
    "Modifiable": true,
    "Name": "MediaId",
    "Order": 0,
    "ShowInGrid": true,
    "Tooltip": "",
    "Id": "5fd17b1b809644c486beea99a039d1c2",
    "CreatedOn": "2016-11-27T13:35:15.7678512Z",
    "UpdatedOn": "2016-11-27T13:35:15.7678512Z"
  },
  {
    "SchemaName": "WechatMaterial",
    "AllowNull": false,
    "ControlType": "TextBox",
    "DefaultValue": "",
    "Indexable": false,
    "IsSystemField": false,
    "Label": "Name",
    "Length": 0,
    "Modifiable": true,
    "Name": "Name",
    "Order": 0,
    "ShowInGrid": true,
    "Tooltip": "",
    "Id": "4779499b9b9542b2bac90cc1c7789c0c",
    "CreatedOn": "2016-11-27T13:35:24.5413531Z",
    "UpdatedOn": "2016-11-27T13:35:24.5413531Z"
  },
  {
    "SchemaName": "WechatMaterial",
    "AllowNull": false,
    "ControlType": "TextBox",
    "DefaultValue": "",
    "Indexable": false,
    "IsSystemField": false,
    "Label": "Description",
    "Length": 0,
    "Modifiable": true,
    "Name": "Description",
    "Order": 0,
    "ShowInGrid": true,
    "Tooltip": "",
    "Id": "f172638bc0904d6182c222f3f7444ad5",
    "CreatedOn": "2016-11-27T13:35:32.4838073Z",
    "UpdatedOn": "2016-11-27T13:35:32.4838073Z"
  },
  {
    "SchemaName": "WechatMaterial",
    "AllowNull": false,
    "ControlType": "TextBox",
    "DefaultValue": "",
    "Indexable": false,
    "IsSystemField": false,
    "Label": "Url",
    "Length": 0,
    "Modifiable": true,
    "Name": "Url",
    "Order": 0,
    "ShowInGrid": true,
    "Tooltip": "",
    "Id": "02bb1c7bc7774edb998f436beb644ee6",
    "CreatedOn": "2016-11-27T13:35:32.4988082Z",
    "UpdatedOn": "2016-11-27T13:35:32.4988082Z"
  },
  {
    "SchemaName": "WechatMaterial",
    "AllowNull": false,
    "ControlType": "TextBox",
    "DefaultValue": "",
    "Indexable": false,
    "IsSystemField": false,
    "Label": "LastUpdateTime",
    "Length": 0,
    "Modifiable": true,
    "Name": "LastUpdateTime",
    "Order": 0,
    "ShowInGrid": true,
    "Tooltip": "",
    "Id": "107be90482114775b1a7876721d59c14",
    "CreatedOn": "2016-11-27T13:35:32.5088088Z",
    "UpdatedOn": "2016-11-27T13:35:32.5088088Z"
  },
  {
    "SchemaName": "WechatMaterial",
    "AllowNull": false,
    "ControlType": "TextBox",
    "DefaultValue": "",
    "Indexable": false,
    "IsSystemField": false,
    "Label": "IsReleased",
    "Length": 0,
    "Modifiable": true,
    "Name": "IsReleased",
    "Order": 0,
    "ShowInGrid": true,
    "Tooltip": "",
    "Id": "3dfd6b0d577f4b0e96e8cfed836c71d5",
    "CreatedOn": "2016-11-27T13:35:32.5158092Z",
    "UpdatedOn": "2016-11-27T13:35:32.5158092Z"
  },
  {
    "SchemaName": "WechatMaterial",
    "AllowNull": false,
    "ControlType": "Hidden",
    "DefaultValue": null,
    "Indexable": false,
    "IsSystemField": true,
    "Label": "Id",
    "Length": 0,
    "Modifiable": false,
    "Name": "Id",
    "Order": 0,
    "ShowInGrid": false,
    "Tooltip": null,
    "Id": "5fdc7f5ba11c406d82e3202b4a33d4f3",
    "CreatedOn": "2016-11-27T13:35:32.5228096Z",
    "UpdatedOn": "2016-11-27T13:35:32.5228096Z"
  },
  {
    "SchemaName": "WechatMaterial",
    "AllowNull": true,
    "ControlType": "TextBox",
    "DefaultValue": "",
    "Indexable": false,
    "IsSystemField": true,
    "Label": "User Key",
    "Length": 0,
    "Modifiable": false,
    "Name": "UserKey",
    "Order": 100,
    "ShowInGrid": false,
    "Tooltip": "An user and SEO friendly content key, it is mostly used to customize the page URL",
    "Id": "d84946f730fe49f5acae7e291d9dc5b3",
    "CreatedOn": "2016-11-27T13:35:32.5278099Z",
    "UpdatedOn": "2016-11-27T13:35:32.5278099Z"
  },
  {
    "SchemaName": "WechatMaterial",
    "AllowNull": true,
    "ControlType": "Hidden",
    "DefaultValue": null,
    "Indexable": false,
    "IsSystemField": true,
    "Label": "Created Time",
    "Length": 0,
    "Modifiable": false,
    "Name": "CreatedOn",
    "Order": 98,
    "ShowInGrid": true,
    "Tooltip": null,
    "Id": "b2a5c11f0dc040fd897c35045bf4d67c",
    "CreatedOn": "2016-11-27T13:35:32.53081Z",
    "UpdatedOn": "2016-11-27T13:35:32.53081Z"
  },
  {
    "SchemaName": "WechatMaterial",
    "AllowNull": false,
    "ControlType": "Hidden",
    "DefaultValue": null,
    "Indexable": false,
    "IsSystemField": true,
    "Label": "Updated Time",
    "Length": 0,
    "Modifiable": false,
    "Name": "UpdatedOn",
    "Order": 98,
    "ShowInGrid": false,
    "Tooltip": null,
    "Id": "3b5bfe0910744e3d929d5be864920af7",
    "CreatedOn": "2016-11-27T13:35:32.5348103Z",
    "UpdatedOn": "2016-11-27T13:35:32.5348103Z"
  },
  {
    "SchemaName": "WechatMaterial",
    "AllowNull": false,
    "ControlType": "Hidden",
    "DefaultValue": null,
    "Indexable": false,
    "IsSystemField": true,
    "Label": "UpdatedBy",
    "Length": 0,
    "Modifiable": false,
    "Name": "UpdatedBy",
    "Order": 99,
    "ShowInGrid": false,
    "Tooltip": null,
    "Id": "49246ff4606d4242a36fbd9aeb87ac4e",
    "CreatedOn": "2016-11-27T13:35:32.5398105Z",
    "UpdatedOn": "2016-11-27T13:35:32.5398105Z"
  },
  {
    "SchemaName": "WechatMaterial",
    "AllowNull": false,
    "ControlType": "Hidden",
    "DefaultValue": null,
    "Indexable": false,
    "IsSystemField": true,
    "Label": "CreatedBy",
    "Length": 0,
    "Modifiable": false,
    "Name": "CreatedBy",
    "Order": 0,
    "ShowInGrid": false,
    "Tooltip": null,
    "Id": "2e369156b6fd4b52a7ab856d6d115fad",
    "CreatedOn": "2016-11-27T13:35:32.5438108Z",
    "UpdatedOn": "2016-11-27T13:35:32.5438108Z"
  },
  {
    "SchemaName": "WechatMaterial",
    "AllowNull": false,
    "ControlType": "Hidden",
    "DefaultValue": null,
    "Indexable": false,
    "IsSystemField": true,
    "Label": "Status",
    "Length": 0,
    "Modifiable": false,
    "Name": "Status",
    "Order": 99,
    "ShowInGrid": false,
    "Tooltip": null,
    "Id": "a225b902fcf94712bbb65087aa5a0f5c",
    "CreatedOn": "2016-11-27T13:35:32.546811Z",
    "UpdatedOn": "2016-11-27T13:35:32.546811Z"
  },
  {
    "SchemaName": "WechatNewsMaterial",
    "AllowNull": false,
    "ControlType": "TextBox",
    "DefaultValue": "",
    "Indexable": false,
    "IsSystemField": false,
    "Label": "OfficialAccount",
    "Length": 0,
    "Modifiable": true,
    "Name": "OfficialAccount",
    "Order": 0,
    "ShowInGrid": true,
    "Tooltip": "",
    "Id": "08d83492358d408bae907de4ac03afb5",
    "CreatedOn": "2016-11-27T14:28:27.9504336Z",
    "UpdatedOn": "2016-11-27T14:28:27.9504336Z"
  },
  {
    "SchemaName": "WechatNewsMaterial",
    "AllowNull": false,
    "ControlType": "TextBox",
    "DefaultValue": "",
    "Indexable": false,
    "IsSystemField": false,
    "Label": "MaterialID",
    "Length": 0,
    "Modifiable": true,
    "Name": "MaterialID",
    "Order": 0,
    "ShowInGrid": true,
    "Tooltip": "",
    "Id": "bb3ff89bd22d41e580d8e172ceff4fcb",
    "CreatedOn": "2016-11-27T14:28:28.0034367Z",
    "UpdatedOn": "2016-11-27T14:28:28.0034367Z"
  },
  {
    "SchemaName": "WechatNewsMaterial",
    "AllowNull": false,
    "ControlType": "TextBox",
    "DefaultValue": "",
    "Indexable": false,
    "IsSystemField": false,
    "Label": "MediaId",
    "Length": 0,
    "Modifiable": true,
    "Name": "MediaId",
    "Order": 0,
    "ShowInGrid": true,
    "Tooltip": "",
    "Id": "5e92eaa59a9c4f91a5f5a7d3faf11a92",
    "CreatedOn": "2016-11-27T14:28:28.0074369Z",
    "UpdatedOn": "2016-11-27T14:28:28.0074369Z"
  },
  {
    "SchemaName": "WechatNewsMaterial",
    "AllowNull": false,
    "ControlType": "TextBox",
    "DefaultValue": "",
    "Indexable": false,
    "IsSystemField": false,
    "Label": "SortBy",
    "Length": 0,
    "Modifiable": true,
    "Name": "SortBy",
    "Order": 0,
    "ShowInGrid": true,
    "Tooltip": "",
    "Id": "c12a2e73814b4327914187ac47a29b8d",
    "CreatedOn": "2016-11-27T14:28:28.0114371Z",
    "UpdatedOn": "2016-11-27T14:28:28.0114371Z"
  },
  {
    "SchemaName": "WechatNewsMaterial",
    "AllowNull": false,
    "ControlType": "TextBox",
    "DefaultValue": "",
    "Indexable": false,
    "IsSystemField": false,
    "Label": "Title",
    "Length": 0,
    "Modifiable": true,
    "Name": "Title",
    "Order": 0,
    "ShowInGrid": true,
    "Tooltip": "",
    "Id": "07348609545a4b6e96509108b8fe8661",
    "CreatedOn": "2016-11-27T14:28:28.0154374Z",
    "UpdatedOn": "2016-11-27T14:28:28.0154374Z"
  },
  {
    "SchemaName": "WechatNewsMaterial",
    "AllowNull": false,
    "ControlType": "TextBox",
    "DefaultValue": "",
    "Indexable": false,
    "IsSystemField": false,
    "Label": "ThumbMediaId",
    "Length": 0,
    "Modifiable": true,
    "Name": "ThumbMediaId",
    "Order": 0,
    "ShowInGrid": true,
    "Tooltip": "",
    "Id": "64596593d1fa4026853149a3c41182c0",
    "CreatedOn": "2016-11-27T14:28:28.0184375Z",
    "UpdatedOn": "2016-11-27T14:28:28.0184375Z"
  },
  {
    "SchemaName": "WechatNewsMaterial",
    "AllowNull": false,
    "ControlType": "TextBox",
    "DefaultValue": "",
    "Indexable": false,
    "IsSystemField": false,
    "Label": "ShowCoverPicture",
    "Length": 0,
    "Modifiable": true,
    "Name": "ShowCoverPicture",
    "Order": 0,
    "ShowInGrid": true,
    "Tooltip": "",
    "Id": "ac87ca54ad9444c19b20ec13feaaa34c",
    "CreatedOn": "2016-11-27T14:28:28.0234378Z",
    "UpdatedOn": "2016-11-27T14:28:28.0234378Z"
  },
  {
    "SchemaName": "WechatNewsMaterial",
    "AllowNull": false,
    "ControlType": "TextBox",
    "DefaultValue": "",
    "Indexable": false,
    "IsSystemField": false,
    "Label": "Author",
    "Length": 0,
    "Modifiable": true,
    "Name": "Author",
    "Order": 0,
    "ShowInGrid": true,
    "Tooltip": "",
    "Id": "85d9710b8c064c7f899d5ed2a1f3947c",
    "CreatedOn": "2016-11-27T14:28:28.0274381Z",
    "UpdatedOn": "2016-11-27T14:28:28.0274381Z"
  },
  {
    "SchemaName": "WechatNewsMaterial",
    "AllowNull": false,
    "ControlType": "TextBox",
    "DefaultValue": "",
    "Indexable": false,
    "IsSystemField": false,
    "Label": "Digest",
    "Length": 0,
    "Modifiable": true,
    "Name": "Digest",
    "Order": 0,
    "ShowInGrid": true,
    "Tooltip": "",
    "Id": "9922e4bfd2c0477daa09118cf086162a",
    "CreatedOn": "2016-11-27T14:28:28.0314383Z",
    "UpdatedOn": "2016-11-27T14:28:28.0314383Z"
  },
  {
    "SchemaName": "WechatNewsMaterial",
    "AllowNull": false,
    "ControlType": "TextBox",
    "DefaultValue": "",
    "Indexable": false,
    "IsSystemField": false,
    "Label": "Content",
    "Length": 0,
    "Modifiable": true,
    "Name": "Content",
    "Order": 0,
    "ShowInGrid": true,
    "Tooltip": "",
    "Id": "a4676eb952ee4e89973fcd2540b21646",
    "CreatedOn": "2016-11-27T14:28:28.0354385Z",
    "UpdatedOn": "2016-11-27T14:28:28.0354385Z"
  },
  {
    "SchemaName": "WechatNewsMaterial",
    "AllowNull": false,
    "ControlType": "TextBox",
    "DefaultValue": "",
    "Indexable": false,
    "IsSystemField": false,
    "Label": "Url",
    "Length": 0,
    "Modifiable": true,
    "Name": "Url",
    "Order": 0,
    "ShowInGrid": true,
    "Tooltip": "",
    "Id": "fd76372a87ea4b489f39435df2af39f3",
    "CreatedOn": "2016-11-27T14:28:28.0394387Z",
    "UpdatedOn": "2016-11-27T14:28:28.0394387Z"
  },
  {
    "SchemaName": "WechatNewsMaterial",
    "AllowNull": false,
    "ControlType": "TextBox",
    "DefaultValue": "",
    "Indexable": false,
    "IsSystemField": false,
    "Label": "ContentSourceUrl",
    "Length": 0,
    "Modifiable": true,
    "Name": "ContentSourceUrl",
    "Order": 0,
    "ShowInGrid": true,
    "Tooltip": "",
    "Id": "42ad4c05e82044a3ac6c1f0b4ae5647d",
    "CreatedOn": "2016-11-27T14:28:28.043439Z",
    "UpdatedOn": "2016-11-27T14:28:28.043439Z"
  },
  {
    "SchemaName": "WechatNewsMaterial",
    "AllowNull": false,
    "ControlType": "TextBox",
    "DefaultValue": "",
    "Indexable": false,
    "IsSystemField": false,
    "Label": "LastUpdateTime",
    "Length": 0,
    "Modifiable": true,
    "Name": "LastUpdateTime",
    "Order": 0,
    "ShowInGrid": true,
    "Tooltip": "",
    "Id": "31ccb9c7265b4d4fbbf6146eae47078f",
    "CreatedOn": "2016-11-27T14:28:28.0474392Z",
    "UpdatedOn": "2016-11-27T14:28:28.0474392Z"
  },
  {
    "SchemaName": "WechatNewsMaterial",
    "AllowNull": false,
    "ControlType": "TextBox",
    "DefaultValue": "",
    "Indexable": false,
    "IsSystemField": false,
    "Label": "IsReleased",
    "Length": 0,
    "Modifiable": true,
    "Name": "IsReleased",
    "Order": 0,
    "ShowInGrid": true,
    "Tooltip": "",
    "Id": "12c505b0d68d4edaab5d880b8ccfe2e8",
    "CreatedOn": "2016-11-27T14:28:28.0514394Z",
    "UpdatedOn": "2016-11-27T14:28:28.0514394Z"
  },
  {
    "SchemaName": "WechatNewsMaterial",
    "AllowNull": false,
    "ControlType": "Hidden",
    "DefaultValue": null,
    "Indexable": false,
    "IsSystemField": true,
    "Label": "Id",
    "Length": 0,
    "Modifiable": false,
    "Name": "Id",
    "Order": 0,
    "ShowInGrid": false,
    "Tooltip": null,
    "Id": "0d58eefeb1d84c21be04c7e3974c1125",
    "CreatedOn": "2016-11-27T14:28:28.0544396Z",
    "UpdatedOn": "2016-11-27T14:28:28.0544396Z"
  },
  {
    "SchemaName": "WechatNewsMaterial",
    "AllowNull": true,
    "ControlType": "TextBox",
    "DefaultValue": "",
    "Indexable": false,
    "IsSystemField": true,
    "Label": "User Key",
    "Length": 0,
    "Modifiable": false,
    "Name": "UserKey",
    "Order": 100,
    "ShowInGrid": false,
    "Tooltip": "An user and SEO friendly content key, it is mostly used to customize the page URL",
    "Id": "b52ae70adc55416d880bbeb6737ee7f2",
    "CreatedOn": "2016-11-27T14:28:28.0584398Z",
    "UpdatedOn": "2016-11-27T14:28:28.0584398Z"
  },
  {
    "SchemaName": "WechatNewsMaterial",
    "AllowNull": true,
    "ControlType": "Hidden",
    "DefaultValue": null,
    "Indexable": false,
    "IsSystemField": true,
    "Label": "Created Time",
    "Length": 0,
    "Modifiable": false,
    "Name": "CreatedOn",
    "Order": 98,
    "ShowInGrid": true,
    "Tooltip": null,
    "Id": "a807e869ae4a4c83a9bb82a6ca1dedcf",
    "CreatedOn": "2016-11-27T14:28:28.0624401Z",
    "UpdatedOn": "2016-11-27T14:28:28.0624401Z"
  },
  {
    "SchemaName": "WechatNewsMaterial",
    "AllowNull": false,
    "ControlType": "Hidden",
    "DefaultValue": null,
    "Indexable": false,
    "IsSystemField": true,
    "Label": "Updated Time",
    "Length": 0,
    "Modifiable": false,
    "Name": "UpdatedOn",
    "Order": 98,
    "ShowInGrid": false,
    "Tooltip": null,
    "Id": "f01bee363153421daf6279a4961cf266",
    "CreatedOn": "2016-11-27T14:28:28.0674403Z",
    "UpdatedOn": "2016-11-27T14:28:28.0674403Z"
  },
  {
    "SchemaName": "WechatNewsMaterial",
    "AllowNull": false,
    "ControlType": "Hidden",
    "DefaultValue": null,
    "Indexable": false,
    "IsSystemField": true,
    "Label": "UpdatedBy",
    "Length": 0,
    "Modifiable": false,
    "Name": "UpdatedBy",
    "Order": 99,
    "ShowInGrid": false,
    "Tooltip": null,
    "Id": "b404704906a946ad954892a9e168d685",
    "CreatedOn": "2016-11-27T14:28:28.0714406Z",
    "UpdatedOn": "2016-11-27T14:28:28.0714406Z"
  },
  {
    "SchemaName": "WechatNewsMaterial",
    "AllowNull": false,
    "ControlType": "Hidden",
    "DefaultValue": null,
    "Indexable": false,
    "IsSystemField": true,
    "Label": "CreatedBy",
    "Length": 0,
    "Modifiable": false,
    "Name": "CreatedBy",
    "Order": 0,
    "ShowInGrid": false,
    "Tooltip": null,
    "Id": "0ed74af04017471f95cc7d31d7f65fd1",
    "CreatedOn": "2016-11-27T14:28:28.0754408Z",
    "UpdatedOn": "2016-11-27T14:28:28.0754408Z"
  },
  {
    "SchemaName": "WechatNewsMaterial",
    "AllowNull": false,
    "ControlType": "Hidden",
    "DefaultValue": null,
    "Indexable": false,
    "IsSystemField": true,
    "Label": "Status",
    "Length": 0,
    "Modifiable": false,
    "Name": "Status",
    "Order": 99,
    "ShowInGrid": false,
    "Tooltip": null,
    "Id": "ae4404a4b52e44668e1400dc97951b4d",
    "CreatedOn": "2016-11-27T14:28:28.0804411Z",
    "UpdatedOn": "2016-11-27T14:28:28.0804411Z"
  }
]